{"chunk_definitions":[{"chunk_id":"c1boiiexfg18a","chunk_label":"unnamed-chunk-1","document_id":"59251671","expansion_state":0,"options":{"engine":"r","label":"unnamed-chunk-15"},"row":55,"row_count":1,"visible":true},{"chunk_id":"cr1fuhc555ncp","chunk_label":"unnamed-chunk-2","document_id":"59251671","expansion_state":0,"options":{"engine":"r","label":"unnamed-chunk-16"},"row":59,"row_count":1,"visible":true},{"chunk_id":"cd1qlk0u4kycg","chunk_label":"unnamed-chunk-3","document_id":"59251671","expansion_state":0,"options":{"engine":"r","label":"unnamed-chunk-17"},"row":68,"row_count":1,"visible":true},{"chunk_id":"c0zk0qtxlv7f5","chunk_label":"unnamed-chunk-4","document_id":"59251671","expansion_state":0,"options":{"engine":"r","label":"unnamed-chunk-18"},"row":74,"row_count":1,"visible":true},{"chunk_id":"cqt43mkjlgji4","chunk_label":"unnamed-chunk-5","document_id":"59251671","expansion_state":0,"options":{"engine":"r","label":"unnamed-chunk-19"},"row":87,"row_count":1,"visible":true},{"chunk_id":"cxzh7m26zr6t5","chunk_label":"unnamed-chunk-6","document_id":"59251671","expansion_state":0,"options":{"engine":"r","label":"unnamed-chunk-20"},"row":91,"row_count":1,"visible":true},{"chunk_id":"c7izxji6pd41c","chunk_label":"unnamed-chunk-7","document_id":"59251671","expansion_state":0,"options":{"engine":"r","label":"unnamed-chunk-21"},"row":99,"row_count":1,"visible":true},{"chunk_id":"cs44lvswg68bb","chunk_label":"unnamed-chunk-8","document_id":"59251671","expansion_state":0,"options":{"engine":"r","label":"unnamed-chunk-22"},"row":103,"row_count":1,"visible":true},{"chunk_id":"c9x8pylsns916","chunk_label":"unnamed-chunk-9","document_id":"59251671","expansion_state":0,"options":{"engine":"r","label":"unnamed-chunk-23"},"row":115,"row_count":1,"visible":true},{"chunk_id":"cc9dnr0b7ylkm","chunk_label":"unnamed-chunk-10","document_id":"59251671","expansion_state":0,"options":{"engine":"r","label":"unnamed-chunk-24"},"row":121,"row_count":1,"visible":true},{"chunk_id":"czhctsola73gc","chunk_label":"unnamed-chunk-11","document_id":"59251671","expansion_state":0,"options":{"engine":"r","label":"unnamed-chunk-25"},"row":126,"row_count":1,"visible":true},{"chunk_id":"cump68fr1y70h","chunk_label":"unnamed-chunk-12","document_id":"59251671","expansion_state":0,"options":{"engine":"r","label":"unnamed-chunk-26"},"row":131,"row_count":1,"visible":true}],"doc_write_time":1547524231}